[
  {
    "animation_name": "Score Update",
    "animation_params": {
      "animation_duration": 10000,
      "animation_objects": [
        {
          "animation_keyframes": [
            {
              "opacity": 0,
              "duration": 0,
              "endDelay": 30
            },
            {
              "opacity": 1,
              "duration": 0,
              "endDelay": 9970
            }
          ],
          "id": "noise_texture"
        },
        {
          "animation_keyframes": [
            {
              "originX": 0,
              "originY": 0,
              "left": {},
              "top": 900,
              "duration": 0,
              "endDelay": 480
            },
            {
              "originX": 0,
              "originY": 0,
              "left": {},
              "top": -1390,
              "duration": 200,
              "endDelay": 0
            },
            {
              "originX": 0,
              "originY": 0,
              "left": {},
              "top": 900,
              "duration": 0,
              "endDelay": 0
            },
            {
              "originX": 0,
              "originY": 0,
              "left": {},
              "top": -1390,
              "duration": 200,
              "endDelay": 0
            },
            {
              "originX": 0,
              "originY": 0,
              "left": {},
              "top": 900,
              "duration": 0,
              "endDelay": 0
            },
            {
              "originX": 0,
              "originY": 0,
              "left": {},
              "top": {},
              "duration": 320,
              "endDelay": 700
            },
            {
              "originX": 0.5,
              "originY": 0.5,
              "left": 225.41975308641975,
              "top": 402.658024691358,
              "scaleX": "*=1.08",
              "scaleY": "*=1.08",
              "duration": 8000,
              "endDelay": 100
            },
            {
              "originX": 0,
              "originY": 0,
              "top": {},
              "left": {},
              "scaleX": {},
              "scaleY": {},
              "duration": 0,
              "endDelay": 0
            }
          ],
          "id": "background_logo"
        },
        {
          "animation_keyframes": [
            {
              "top": 902,
              "duration": 0,
              "endDelay": 1100
            },
            {
              "top": {},
              "duration": 240,
              "endDelay": 8660
            }
          ],
          "id": "accent_logo_background"
        },
        {
          "animation_keyframes": [
            {
              "left": 729,
              "top": 30,
              "duration": 0,
              "endDelay": 1100
            },
            {
              "left": {},
              "top": {},
              "duration": 400,
              "endDelay": 500
            },
            {
              "left": 333,
              "top": {},
              "duration": 2000,
              "endDelay": 0,
              "easing": "easeOutSine"
            },
            {
              "left": 353,
              "top": {},
              "duration": 2000,
              "endDelay": 0,
              "easing": "easeOutSine"
            },
            {
              "left": 333,
              "top": {},
              "duration": 2000,
              "endDelay": 0,
              "easing": "easeOutSine"
            },
            {
              "left": {},
              "top": {},
              "duration": 2000,
              "endDelay": 0
            }
          ],
          "id": "accent_logo"
        },
        {
          "animation_keyframes": [
            {
              "top": -905,
              "duration": 0,
              "endDelay": 1300
            },
            {
              "top": {},
              "duration": 140,
              "endDelay": 8560
            }
          ],
          "id": "additional_inform_rect"
        },
        {
          "animation_keyframes": [
            {
              "left": -905,
              "duration": 0,
              "endDelay": 1100
            },
            {
              "left": {},
              "duration": 400,
              "endDelay": 8500
            }
          ],
          "id": {
            "id": "subtitle_rect",
            "element": "clipPath"
          }
        },
        {
          "animation_keyframes": [
            {
              "left": -905,
              "duration": 0,
              "endDelay": 1100
            },
            {
              "left": {},
              "duration": 300,
              "endDelay": 8600
            }
          ],
          "id": {
            "id": "subtitle",
            "element": "clipPath"
          }
        },
        {
          "animation_keyframes": [
            {
              "left": -905,
              "duration": 0,
              "endDelay": 1120
            },
            {
              "left": {},
              "duration": 430,
              "endDelay": 8450
            }
          ],
          "id": {
            "id": "title_1",
            "element": "clipPath"
          }
        },
        {
          "animation_keyframes": [
            {
              "left": -905,
              "duration": 0,
              "endDelay": 1600
            },
            {
              "left": {},
              "duration": 250,
              "endDelay": 8150
            }
          ],
          "id": {
            "id": "title_2",
            "element": "clipPath"
          }
        },
        {
          "animation_keyframes": [
            {
              "top": -905,
              "duration": 0,
              "endDelay": 1400
            },
            {
              "top": {},
              "duration": 600,
              "endDelay": 8000
            }
          ],
          "id": {
            "id": "group_1",
            "element": "clipPath"
          }
        },
        {
          "animation_keyframes": [
            {
              "top": 905,
              "duration": 0,
              "endDelay": 1400
            },
            {
              "top": {},
              "duration": 450,
              "endDelay": 8150
            }
          ],
          "id": {
            "id": "group_2",
            "element": "clipPath"
          }
        },
        {
          "animation_keyframes": [
            {
              "originX": 0.5,
              "originY": 0.5,
              "left": 367.3,
              "top": 311,
              "scaleX": {},
              "scaleY": {},
              "duration": 0,
              "endDelay": 1500
            },
            {
              "left": 367.3,
              "top": 311,
              "scaleX": {},
              "scaleY": {},
              "duration": 700,
              "endDelay": 600
            },
            {
              "scaleX": "*=0.9",
              "scaleY": "*=0.9",
              "duration": 1000,
              "endDelay": 0
            },
            {
              "scaleX": {},
              "scaleY": {},
              "duration": 1000,
              "endDelay": 0
            },
            {
              "scaleX": "*=0.9",
              "scaleY": "*=0.9",
              "duration": 1000,
              "endDelay": 0
            },
            {
              "scaleX": {},
              "scaleY": {},
              "duration": 1000,
              "endDelay": 0
            },
            {
              "scaleX": "*=0.9",
              "scaleY": "*=0.9",
              "duration": 1000,
              "endDelay": 0
            },
            {
              "originX": 0,
              "originY": 0,
              "left": {},
              "top": {},
              "scaleX": {},
              "scaleY": {},
              "duration": 1000,
              "endDelay": 1200
            }
          ],
          "id": "group_1"
        },
        {
          "animation_keyframes": [
            {
              "originX": 0.5,
              "originY": 0.5,
              "left": 367.3,
              "top": 586.5,
              "scaleX": {},
              "scaleY": {},
              "duration": 0,
              "endDelay": 1800
            },
            {
              "left": 367.3,
              "top": 586.5,
              "scaleX": {},
              "scaleY": {},
              "duration": 700,
              "endDelay": 600
            },
            {
              "scaleX": "*=0.9",
              "scaleY": "*=0.9",
              "duration": 1000,
              "endDelay": 0
            },
            {
              "scaleX": {},
              "scaleY": {},
              "duration": 1000,
              "endDelay": 0
            },
            {
              "scaleX": "*=0.9",
              "scaleY": "*=0.9",
              "duration": 1000,
              "endDelay": 0
            },
            {
              "scaleX": {},
              "scaleY": {},
              "duration": 1000,
              "endDelay": 0
            },
            {
              "scaleX": "*=0.9",
              "scaleY": "*=0.9",
              "duration": 1000,
              "endDelay": 0
            },
            {
              "originX": 0,
              "originY": 0,
              "left": {},
              "top": {},
              "scaleX": {},
              "scaleY": {},
              "duration": 1000,
              "endDelay": 900
            }
          ],
          "id": "group_2"
        },
        {
          "animation_keyframes": [
            {
              "text": "0",
              "opacity": 0,
              "duration": 0,
              "endDelay": 1850
            },
            {
              "opacity": 1,
              "duration": 400,
              "endDelay": 0
            },
            {
              "text": {},
              "duration": 1500,
              "round": 1,
              "endDelay": 6200
            }
          ],
          "id": "team_1_score"
        },
        {
          "animation_keyframes": [
            {
              "text": "0",
              "opacity": 0,
              "duration": 0,
              "endDelay": 1850
            },
            {
              "opacity": 1,
              "duration": 400,
              "endDelay": 0
            },
            {
              "text": {},
              "duration": 1500,
              "round": 1,
              "endDelay": 6200
            }
          ],
          "id": "team_2_score"
        }
      ]
    }
  }
]